[
  {
    "name": "A TAMIRCISI",
    "sector": "YEDEK PARCA",
    "address_line1": "M SINAN MAH USKUDAR CD NO:59",
    "address_line2": "USKUDAR / ISTANBUL",
    "phone1": "0216 111 11 11",
    "phone2": "",
    "website": "",
    "tax_office": "",
    "trade_registry_no": "",
    "eku_no": "",
    "z_no": "",
    "footer_logo_code": "",
    "game_code": "OYK-001",
    "default_product": "YEDEK PARCA",
    "default_vat": 20.0,
    "default_amount": 3750.0
  },
  {
    "name": "B MARKET",
    "sector": "MARKET ALISVERISI",
    "address_line1": "ATATURK CAD NO:11",
    "address_line2": "KADIKOY / ISTANBUL",
    "phone1": "0216 222 22 22",
    "phone2": "",
    "website": "",
    "tax_office": "",
    "trade_registry_no": "",
    "eku_no": "",
    "z_no": "",
    "footer_logo_code": "",
    "game_code": "OYK-002",
    "default_product": "MARKET URUNU",
    "default_vat": 10.0,
    "default_amount": 420.0
  },
  {
    "name": "C BENZINLIK",
    "sector": "AKARYAKIT",
    "address_line1": "CEVRE YOLU KM 5",
    "address_line2": "UMRANIYE / ISTANBUL",
    "phone1": "0216 333 33 33",
    "phone2": "",
    "website": "",
    "tax_office": "",
    "trade_registry_no": "",
    "eku_no": "",
    "z_no": "",
    "footer_logo_code": "",
    "game_code": "OYK-003",
    "default_product": "AKARYAKIT",
    "default_vat": 20.0,
    "default_amount": 1250.0
  },
  {
    "name": "D ECZANE",
    "sector": "ILAC",
    "address_line1": "SAGLIK SOK NO:8",
    "address_line2": "USKUDAR / ISTANBUL",
    "phone1": "0216 444 44 44",
    "phone2": "",
    "website": "",
    "tax_office": "",
    "trade_registry_no": "",
    "eku_no": "",
    "z_no": "",
    "footer_logo_code": "",
    "game_code": "OYK-004",
    "default_product": "ILAC",
    "default_vat": 10.0,
    "default_amount": 890.0
  },
  {
    "name": "E RESTORAN",
    "sector": "YEMEK",
    "address_line1": "LEZZET CAD NO:27",
    "address_line2": "BESIKTAS / ISTANBUL",
    "phone1": "0216 555 55 55",
    "phone2": "",
    "website": "",
    "tax_office": "",
    "trade_registry_no": "",
    "eku_no": "",
    "z_no": "",
    "footer_logo_code": "",
    "game_code": "OYK-005",
    "default_product": "YEMEK SERVISI",
    "default_vat": 10.0,
    "default_amount": 640.0
  }
]